<annotation>
	<folder>Raw</folder>
	<filename>1231neg.jpg</filename>
	<path>C:\Users\HOME\Desktop\NeuroNEt\Raw\1231neg.jpg</path>
	<source>
		<database>Unknown</database>
	</source>
	<size>
		<width>0</width>
		<height>0</height>
		<depth>3</depth>
	</size>
	<segmented>0</segmented>
	<object>
		<name>pesh</name>
		<pose>Unspecified</pose>
		<truncated>0</truncated>
		<difficult>0</difficult>
		<bndbox>
			<xmin>312</xmin>
			<ymin>118</ymin>
			<xmax>370</xmax>
			<ymax>177</ymax>
		</bndbox>
	</object>
	<object>
		<name>prep</name>
		<pose>Unspecified</pose>
		<truncated>0</truncated>
		<difficult>0</difficult>
		<bndbox>
			<xmin>265</xmin>
			<ymin>149</ymin>
			<xmax>302</xmax>
			<ymax>183</ymax>
		</bndbox>
	</object>
</annotation>
