<annotation>
	<folder>Raw</folder>
	<filename>1955neg.jpg</filename>
	<path>C:\Users\HOME\Desktop\NeuroNEt\Raw\1955neg.jpg</path>
	<source>
		<database>Unknown</database>
	</source>
	<size>
		<width>0</width>
		<height>0</height>
		<depth>3</depth>
	</size>
	<segmented>0</segmented>
	<object>
		<name>Stop</name>
		<pose>Unspecified</pose>
		<truncated>0</truncated>
		<difficult>0</difficult>
		<bndbox>
			<xmin>539</xmin>
			<ymin>113</ymin>
			<xmax>601</xmax>
			<ymax>172</ymax>
		</bndbox>
	</object>
</annotation>
