<annotation>
	<folder>Raw</folder>
	<filename>669neg.jpg</filename>
	<path>C:\Users\HOME\Desktop\NeuroNEt\Raw\669neg.jpg</path>
	<source>
		<database>Unknown</database>
	</source>
	<size>
		<width>0</width>
		<height>0</height>
		<depth>3</depth>
	</size>
	<segmented>0</segmented>
	<object>
		<name>pesh</name>
		<pose>Unspecified</pose>
		<truncated>0</truncated>
		<difficult>0</difficult>
		<bndbox>
			<xmin>200</xmin>
			<ymin>131</ymin>
			<xmax>247</xmax>
			<ymax>180</ymax>
		</bndbox>
	</object>
	<object>
		<name>forw</name>
		<pose>Unspecified</pose>
		<truncated>0</truncated>
		<difficult>0</difficult>
		<bndbox>
			<xmin>411</xmin>
			<ymin>19</ymin>
			<xmax>551</xmax>
			<ymax>149</ymax>
		</bndbox>
	</object>
</annotation>
