<annotation>
	<folder>Костя</folder>
	<filename>sing2_5351 _res.jpg</filename>
	<path>C:\Users\HOME\Desktop\Костя\sing2_5351 _res.jpg</path>
	<source>
		<database>Unknown</database>
	</source>
	<size>
		<width>640</width>
		<height>480</height>
		<depth>3</depth>
	</size>
	<segmented>0</segmented>
	<object>
		<name>Right</name>
		<pose>Unspecified</pose>
		<truncated>0</truncated>
		<difficult>0</difficult>
		<bndbox>
			<xmin>386</xmin>
			<ymin>130</ymin>
			<xmax>458</xmax>
			<ymax>208</ymax>
		</bndbox>
	</object>
	<object>
		<name>Nerov</name>
		<pose>Unspecified</pose>
		<truncated>0</truncated>
		<difficult>0</difficult>
		<bndbox>
			<xmin>244</xmin>
			<ymin>137</ymin>
			<xmax>283</xmax>
			<ymax>173</ymax>
		</bndbox>
	</object>
</annotation>
