<annotation>
	<folder>Вова</folder>
	<filename>sing_2419 _res.jpg</filename>
	<path>C:\Users\youbo\Desktop\Вова\sing_2419 _res.jpg</path>
	<source>
		<database>Unknown</database>
	</source>
	<size>
		<width>640</width>
		<height>480</height>
		<depth>3</depth>
	</size>
	<segmented>0</segmented>
	<object>
		<name>Stop</name>
		<pose>Unspecified</pose>
		<truncated>0</truncated>
		<difficult>0</difficult>
		<bndbox>
			<xmin>485</xmin>
			<ymin>223</ymin>
			<xmax>518</xmax>
			<ymax>254</ymax>
		</bndbox>
	</object>
</annotation>
